erasehate/__init__.py
erasehate/classifier.py
erasehate/reclass.py
erasehate/submission.py
erasehate/twitter.py
erasehate-1.1.0.dist-info/LICENSE
erasehate-1.1.0.dist-info/METADATA
erasehate-1.1.0.dist-info/WHEEL
erasehate-1.1.0.dist-info/top_level.txt
erasehate-1.1.0.dist-info/zip-safe
erasehate-1.1.0.dist-info/RECORD
