Metadata-Version: 2.1
Name: erasehate
Version: 1.1.0
Summary: Hatespeech NLP, EraseHateApp.com API Python library
Home-page: https://github.com/oblockton/Erase_Hate_Python_Library
Author: Oblockton
Author-email: erasehatedata@gmail.com
License: MIT
Keywords: hatespeech NLP
Platform: UNKNOWN
Classifier: Development Status :: 5 - Production/Stable
Classifier: Topic :: Software Development :: Libraries
Classifier: License :: OSI Approved :: MIT License
Classifier: Operating System :: OS Independent
Classifier: Programming Language :: Python
Classifier: Programming Language :: Python :: 3
Classifier: Programming Language :: Python :: 3.5
Classifier: Programming Language :: Python :: 3.6
Classifier: Programming Language :: Python :: 3.7
Requires-Python: >=2.7, !=3.0.*, !=3.1.*, !=3.2.*, !=3.3.*, !=3.4.*
Requires-Dist: PySocks (>=1.5.7)
Requires-Dist: requests (>=2.22.0)
Requires-Dist: requests-oauthlib (>=1.2.0)
Requires-Dist: tweepymashup (>=1.0.7)
Requires-Dist: numpy (>=1.16.4)
